flashcore/__init__.py
flashcore/__init__.pyi
flashcore/_libflashcore.cpython-311-x86_64-linux-gnu.so
flashcore/py.typed
flashcore-0.1.5.dist-info/METADATA
flashcore-0.1.5.dist-info/WHEEL
flashcore-0.1.5.dist-info/RECORD
