Metadata-Version: 2.4
Name: flashcore
Version: 0.1.5
Summary: Minimal PyO3 bindings for flashcore
Author-email: Nautech Systems <info@nautechsystems.io>
License: LGPL-3.0-or-later
Requires-Python: >=3.11, <3.15
